<?xml version="1.0" encoding="utf-8"?>
<executable>
  <category>
  Statistics
  </category>
  <title>
  Label Diameter Estimation
  </title>
  <description>
  Estimates the largest diameter of a label, saved as a list of endpoint
  fiducials in a file.
  </description>
  <version>1.3</version>
  <documentation-url></documentation-url>
  <license></license>
  <contributor>Andriy Fedorov</contributor>
<acknowledgements>
This work was supported by funding from Brain Science Foundation.
</acknowledgements>

  <parameters>
    <label> Parameters</label>
    <description>Parameters for diameter estimation</description>

    <integer>
      <name>inputLabel</name>
      <longflag>--label</longflag>
      <description>The value of the label that should be used for diameter estimation. If set to 0, all non-zero values in the input image will be considered as one label.</description>
      <label>Label value</label>
      <default>0</default>
    </integer>

  </parameters>

  <parameters>
    <label>IO</label>
    <description>Input/output parameters</description>
    <image>
      <name>inputVolume</name>
      <label>Input Volume</label>
      <channel>input</channel>
      <index>0</index>
      <description>Input volume to be segmented</description>
    </image>

    <image type="label">
      <name>outputDiameters</name>
      <label>Output label image</label>
      <channel>output</channel>
      <index>1</index>
      <description>Output label image will show the identified diameters</description>
    </image>

    <file fileExtensions=".fcvs">
      <name>outputFiducialFile</name>
      <label>File to keep the output fiducials</label>
      <channel>output</channel>
      <index>2</index>
      <description>File to save the list of fiducials corresponding to the
      identified diameters</description>
    </file>

  </parameters>
</executable>
